downstream_fairness/__init__.py
downstream_fairness/process.py
downstream_fairness/train.py
downstream_fairness/version.py
downstream_fairness/utils/barycenter.py
downstream_fairness/utils/constants.py
downstream_fairness/utils/metrics.py
downstream_fairness-0.1.1.dist-info/LICENSE.txt
downstream_fairness-0.1.1.dist-info/METADATA
downstream_fairness-0.1.1.dist-info/WHEEL
downstream_fairness-0.1.1.dist-info/top_level.txt
downstream_fairness-0.1.1.dist-info/RECORD
