Metadata-Version: 2.1
Name: downstream-fairness
Version: 0.1.1
Summary: A new post-processing fairness algorithm that operates on the output probabilities of a binary classifier
Author-email: Arthur <info@arthur.ai>, Daniel Nissani <daniel.nissani@arthur.ai>
License: MIT
Project-URL: Homepage, http://arthur.ai
Project-URL: Repository, https://github.com/arthur-ai/downstream-fairness
Classifier: Development Status :: 5 - Production/Stable
Classifier: Programming Language :: Python :: 3.8
Classifier: Programming Language :: Python :: 3.9
Classifier: Programming Language :: Python :: 3.10
Classifier: Programming Language :: Python :: 3.11
License-File: LICENSE.txt
Requires-Dist: numpy (<2,>=1.19.0)
Requires-Dist: pandas (>=1.2.0)
Requires-Dist: POT (==0.9.0)
Requires-Dist: python-dateutil (<3,>=2.7)
Requires-Dist: pytz (>=2020.1)
Requires-Dist: scipy (~=1.10.1)
Requires-Dist: tzdata (==2020.1)
